edpfw/__init__.py
edplib/__init__.py
edp-0.0.1.dist-info/LICENSE
edp-0.0.1.dist-info/METADATA
edp-0.0.1.dist-info/WHEEL
edp-0.0.1.dist-info/top_level.txt
edp-0.0.1.dist-info/RECORD
