Metadata-Version: 2.1
Name: edp
Version: 0.0.1
Summary: A cloud native rapid application deployment platform + data management toolkit
Author-email: Alex Arnesen <alexarnesen@gmail.com>
Maintainer-email: Alex Arnesen <alexarnesen@gmail.com>
Keywords: business,data,platform,cloud,ETL,Azure
Requires-Python: >=3.10
License-File: LICENSE
Requires-Dist: requests
